{"name":"Allure Report","stats":{"total":20,"passed":20},"status":"passed","duration":5679,"createdAt":1770256225062,"plugin":"Awesome","newTests":[{"id":"5e299874b6c5c931cc49fb70b588338e","name":"test_user_login","status":"passed","duration":303},{"id":"12d31518f2ca29115c7e44d9b29aed86","name":"test_list_cars[no_params]","status":"passed","duration":429},{"id":"f753a442221f53766992e518ca53d27b","name":"test_services_list[limit_1]","status":"passed","duration":244},{"id":"557582dd8de7ee7fac6b3a679a143caf","name":"test_list_customers[limit_1_offset_1]","status":"passed","duration":290},{"id":"fd1b3ce01ae7efa779ee6c4af1247b1d","name":"test_list_car_engines[limit_1_offset_1]","status":"passed","duration":212},{"id":"4e1b60c9275c41e256960f49963c1e6b","name":"test_operations_list[limit_1]","status":"passed","duration":197},{"id":"1b2d0304a94a2662be0cef46b49c3850","name":"test_operations_list[no_params]","status":"passed","duration":260},{"id":"27e0c2facfddd725c4c6016b3c65a706","name":"test_payments_list[limit_1]","status":"passed","duration":199},{"id":"77da7b8811a0f6f76c9124dfa8ff406f","name":"test_services_list[limit_1_offset_1]","status":"passed","duration":451},{"id":"c22170da46004904935703c22769e210","name":"test_payments_list[limit_1_offset_1]","status":"passed","duration":199},{"id":"18c2e567abcf61085bf610b60d3c9031","name":"test_list_customers[limit_1]","status":"passed","duration":197},{"id":"109d3bc053fe4e4ff5ad0e55f880bfb7","name":"test_list_customers[no_params]","status":"passed","duration":266},{"id":"16197751c151ec4e2a0cf3e9595d0e2e","name":"test_operations_list[limit_1_offset_1]","status":"passed","duration":259},{"id":"d0ea3ae303ee5856c27af56c4fdda5c9","name":"test_payments_list[no_params]","status":"passed","duration":203},{"id":"714cce6d2efcc36b32db5dae20b2040f","name":"test_root_list","status":"passed","duration":696},{"id":"d32348dcb57a2f242b3d6a44c6b542b5","name":"test_list_car_engines[no_params]","status":"passed","duration":212},{"id":"f0fb71fced305c16551745dc7a5b6c85","name":"test_list_cars[limit_1_offset_1]","status":"passed","duration":193},{"id":"a39c36447b56dd229432143f897c94a2","name":"test_list_cars[limit_1]","status":"passed","duration":216},{"id":"971cc31f0aaefa1b4b993d17265be210","name":"test_services_list[no_params]","status":"passed","duration":244},{"id":"457bb48f19d989f9533117486cf68886","name":"test_list_car_engines[limit_1]","status":"passed","duration":409}],"flakyTests":[],"retryTests":[],"meta":{"reportId":"cd6ee9a3-88e2-4a29-84e4-47dc9632558e","singleFile":false,"withTestResultsLinks":true},"pullRequestHref":"","jobHref":"https://github.com/BohdanObruch/wexler_garage_api/actions/runs/21695619613"}